{
    "schema":  "pie.cross.repo.baseline.revocation.v1",
    "baseline_id":  "selftest.cross_repo.lineage.old.v1",
    "reason_code":  "SUPERSEDED_BY_LINEAGE_AUDIT",
    "notes":  "lineage audit selftest revocation",
    "promotion":  "C:\\dev\\pie\\memory\\baselines\\cross_repo\\selftest.cross_repo.lineage.old.v1.promotion.json",
    "promotion_sha256":  "73010bd66c224a07bc9550f91ac2e993c15ba2583f67860ee8030b471e8dc8a4",
    "aggregate":  "C:\\dev\\pie\\memory\\baselines\\cross_repo\\selftest.cross_repo.lineage.old.v1.aggregate.json",
    "aggregate_sha256":  "b5e8ad6f9bb439c006073b1e105542ceb40e94e8e6f97331eef68b868b39f260",
    "previous_promotion_aggregate_sha256":  "b5e8ad6f9bb439c006073b1e105542ceb40e94e8e6f97331eef68b868b39f260",
    "revoked":  true,
    "created_utc":  "2026-06-08T20:40:29.4956743Z"
}
